target_singer_jsonl/__init__.py
target_singer_jsonl-0.1.0.dist-info/WHEEL
target_singer_jsonl-0.1.0.dist-info/METADATA
target_singer_jsonl-0.1.0.dist-info/entry_points.txt
target_singer_jsonl-0.1.0.dist-info/RECORD
